txn_msg_parser/__init__.py
txn_msg_parser/ai.py
txn_msg_parser/constants.py
txn_msg_parser/main.py
txn_msg_parser/prompt.py
txn_msg_parser/training_data/__init__.py
txn_msg_parser/training_data/sms_training.py
txn_msg_parser-0.1.1.dist-info/METADATA
txn_msg_parser-0.1.1.dist-info/WHEEL
txn_msg_parser-0.1.1.dist-info/top_level.txt
txn_msg_parser-0.1.1.dist-info/RECORD
