Metadata-Version: 2.4
Name: txn-msg-parser
Version: 0.1.1
Summary: A Python package for parsing transaction SMS messages into structured transaction dictionaries
Author-email: Vandan Rogheliya <vandan.rogheliya@gmail.com>
License-Expression: MIT
Project-URL: Homepage, https://github.com/VandanRogheliya/txn_msg_parser
Project-URL: Repository, https://github.com/VandanRogheliya/txn_msg_parser
Project-URL: Issues, https://github.com/VandanRogheliya/txn_msg_parser/issues
Keywords: transaction,sms,parser,banking
Classifier: Development Status :: 3 - Alpha
Classifier: Intended Audience :: Developers
Classifier: Programming Language :: Python :: 3
Classifier: Programming Language :: Python :: 3.8
Classifier: Programming Language :: Python :: 3.9
Classifier: Programming Language :: Python :: 3.10
Classifier: Programming Language :: Python :: 3.11
Classifier: Programming Language :: Python :: 3.12
Requires-Python: >=3.8
Requires-Dist: ollama>=0.1.0
Provides-Extra: dev
Requires-Dist: build>=1.0.0; extra == "dev"
